README.rst
setup.py
pywkher/__init__.py
pywkher/bin/wkhtmltopdf-heroku
pywkher_new_params.egg-info/PKG-INFO
pywkher_new_params.egg-info/SOURCES.txt
pywkher_new_params.egg-info/dependency_links.txt
pywkher_new_params.egg-info/not-zip-safe
pywkher_new_params.egg-info/requires.txt
pywkher_new_params.egg-info/top_level.txt