Metadata-Version: 1.1
Name: pywkher-new-params
Version: 1.0.4
Summary: wkhtmltopdf for Python on Heroku
Home-page: https://github.com/rsenkbeil/pywkher
Author: Ryan Senkbeil
Author-email: ryan.senkbeil@gsdesign.com
License: UNKNOWN
Platform: UNKNOWN
Classifier: Development Status :: 4 - Beta
Classifier: Environment :: Web Environment
Classifier: Intended Audience :: Developers
Classifier: License :: OSI Approved :: BSD License
Classifier: Operating System :: OS Independent
Classifier: Programming Language :: Python
Classifier: Programming Language :: Python :: 2.6
Classifier: Programming Language :: Python :: 2.7
Classifier: Topic :: Internet :: WWW/HTTP
Classifier: Topic :: Internet :: WWW/HTTP :: Dynamic Content
Classifier: Topic :: Software Development :: Libraries :: Python Modules
